README.md
setup.py
watchng.1
bin/watchng
watchng/__init__.py
watchng.egg-info/PKG-INFO
watchng.egg-info/SOURCES.txt
watchng.egg-info/dependency_links.txt
watchng.egg-info/top_level.txt